pybaselib/__init__.py
pybaselib/common_models/__init__.py
pybaselib/common_models/filters.py
pybaselib/common_models/managers.py
pybaselib/common_models/models.py
pybaselib/common_models/pagination.py
pybaselib/common_models/serializers.py
pybaselib/factories/__init__.py
pybaselib/factories/factory_registry.py
pybaselib/factories/factories/__init__.py
pybaselib/factories/factories/snmp_factory.py
pybaselib/interfaces/__init__.py
pybaselib/interfaces/dataObject/__init__.py
pybaselib/interfaces/dataObject/string_type.py
pybaselib/interfaces/imgs/__init__.py
pybaselib/interfaces/imgs/img.py
pybaselib/interfaces/imgs/save_img.py
pybaselib/securityTest/__init__.py
pybaselib/securityTest/excel.py
pybaselib/securityTest/xlsx_bomb_generator.py
pybaselib/securityTest/xlsx_bomb_generator_new.py
pybaselib/utils/__init__.py
pybaselib/utils/dynamic_import.py
pybaselib/utils/appLayer/__init__.py
pybaselib/utils/appLayer/base.py
pybaselib/utils/appLayer/ssh_connect.py
pybaselib/utils/appLayer/http/__init__.py
pybaselib/utils/appLayer/http/http2.py
pybaselib/utils/appLayer/http/http2_async.py
pybaselib/utils/appLayer/http/http_client.py
pybaselib/utils/appLayer/mqtt/__init__.py
pybaselib/utils/appLayer/mqtt/b.py
pybaselib/utils/appLayer/mqtt/base.py
pybaselib/utils/appLayer/mqtt/notify.py
pybaselib/utils/appLayer/mqtt/sr_pro_pb2.py
pybaselib/utils/appLayer/mqtt/stress_nw.py
pybaselib/utils/appLayer/mqtt/stress_test.py
pybaselib/utils/appLayer/ntcip/__init__.py
pybaselib/utils/appLayer/ntcip/ntcip_type_parameter.py
pybaselib/utils/appLayer/snmp/__init__.py
pybaselib/utils/appLayer/snmp/compile_mib.py
pybaselib/utils/appLayer/snmp/smi_opr.py
pybaselib/utils/appLayer/snmp/snmpEngine.py
pybaselib/utils/appLayer/tcp/__init__.py
pybaselib/utils/appLayer/udp/__init__.py
pybaselib/utils/appLayer/udp/udp_client.py
pybaselib/utils/cal/__init__.py
pybaselib/utils/cal/code.py
pybaselib/utils/cal/coordinate.py
pybaselib/utils/dataObject/__init__.py
pybaselib/utils/dataObject/int_type.py
pybaselib-1.0.3.dist-info/METADATA
pybaselib-1.0.3.dist-info/WHEEL
pybaselib-1.0.3.dist-info/top_level.txt
pybaselib-1.0.3.dist-info/RECORD
