Metadata-Version: 2.2
Name: pybaselib
Version: 1.0.3
Summary: base lib
Home-page: 
Author: maoyongfan
Author-email: maoyongfan@163.com
Classifier: Programming Language :: Python :: 3
Classifier: License :: OSI Approved :: MIT License
Classifier: Operating System :: OS Independent
Requires-Python: >=3.6
Dynamic: author
Dynamic: author-email
Dynamic: classifier
Dynamic: description
Dynamic: description-content-type
Dynamic: requires-python
Dynamic: summary
